byteArk/__init__.py
byteArk/chardet/__init__.py
byteArk/chardet/big5freq.py
byteArk/chardet/big5prober.py
byteArk/chardet/chardistribution.py
byteArk/chardet/charsetgroupprober.py
byteArk/chardet/charsetprober.py
byteArk/chardet/codingstatemachine.py
byteArk/chardet/compat.py
byteArk/chardet/cp949prober.py
byteArk/chardet/enums.py
byteArk/chardet/escprober.py
byteArk/chardet/escsm.py
byteArk/chardet/eucjpprober.py
byteArk/chardet/euckrfreq.py
byteArk/chardet/euckrprober.py
byteArk/chardet/euctwfreq.py
byteArk/chardet/euctwprober.py
byteArk/chardet/gb2312freq.py
byteArk/chardet/gb2312prober.py
byteArk/chardet/hebrewprober.py
byteArk/chardet/jisfreq.py
byteArk/chardet/jpcntx.py
byteArk/chardet/langbulgarianmodel.py
byteArk/chardet/langcyrillicmodel.py
byteArk/chardet/langgreekmodel.py
byteArk/chardet/langhebrewmodel.py
byteArk/chardet/langhungarianmodel.py
byteArk/chardet/langthaimodel.py
byteArk/chardet/langturkishmodel.py
byteArk/chardet/latin1prober.py
byteArk/chardet/mbcharsetprober.py
byteArk/chardet/mbcsgroupprober.py
byteArk/chardet/mbcssm.py
byteArk/chardet/sbcharsetprober.py
byteArk/chardet/sbcsgroupprober.py
byteArk/chardet/sjisprober.py
byteArk/chardet/universaldetector.py
byteArk/chardet/utf8prober.py
byteArk/chardet/version.py
byteArk/chardet/cli/__init__.py
byteArk/chardet/cli/chardetect.py
byteArk/idna/__init__.py
byteArk/idna/codec.py
byteArk/idna/compat.py
byteArk/idna/core.py
byteArk/idna/idnadata.py
byteArk/idna/intranges.py
byteArk/idna/package_data.py
byteArk/idna/uts46data.py
byteArk/requests/__init__.py
byteArk/requests/__version__.py
byteArk/requests/_internal_utils.py
byteArk/requests/adapters.py
byteArk/requests/api.py
byteArk/requests/auth.py
byteArk/requests/certs.py
byteArk/requests/compat.py
byteArk/requests/cookies.py
byteArk/requests/exceptions.py
byteArk/requests/help.py
byteArk/requests/hooks.py
byteArk/requests/models.py
byteArk/requests/packages.py
byteArk-0.0.12.dist-info/METADATA
byteArk-0.0.12.dist-info/RECORD
byteArk-0.0.12.dist-info/WHEEL
byteArk-0.0.12.dist-info/top_level.txt
