Metadata-Version: 2.1
Name: byteArk
Version: 0.0.12
Summary: Kundjanasith's package
Home-page: https://github.com/pypa/sampleproject
Author: Kundjanasith Thonglek
Author-email: kundjanasith.t@ku.th
License: UNKNOWN
Platform: UNKNOWN
Classifier: Programming Language :: Python :: 3
Classifier: License :: OSI Approved :: MIT License
Classifier: Operating System :: OS Independent
